simple_twitter/__init__.py
simple_twitter/exceptions.py
simple_twitter/tweets_search_stream.py
simple_twitter-0.0.1.dist-info/LICENSE
simple_twitter-0.0.1.dist-info/METADATA
simple_twitter-0.0.1.dist-info/WHEEL
simple_twitter-0.0.1.dist-info/top_level.txt
simple_twitter-0.0.1.dist-info/RECORD
