Metadata-Version: 2.1
Name: simple-twitter
Version: 0.0.1
Summary: A module to simplify the Twitter extraction
Home-page: https://github.com/mbiemann/simple-twitter
Author: Marcell Biemann
Author-email: mbiemann@gmail.com
License: UNKNOWN
Project-URL: Bug Tracker, https://github.com/mbiemann/simple-twitter/issues
Platform: UNKNOWN
Classifier: Programming Language :: Python :: 3
Classifier: License :: OSI Approved :: MIT License
Classifier: Operating System :: OS Independent
Requires-Python: >=3.6
License-File: LICENSE
Requires-Dist: requests (==2.26.0)
